keylimiter/__init__.py
keylimiter/__init__.pyi
keylimiter/key_limiter.py
keylimiter/keyvalue_store/__init__.py
keylimiter/keyvalue_store/in_memory_ttl.py
keylimiter/keyvalue_store/keyvalue_store.py
keylimiter/sliding_window_counter.py
keylimiter/token_bucket.py
keylimiter-0.1.5.dist-info/LICENSE
keylimiter-0.1.5.dist-info/METADATA
keylimiter-0.1.5.dist-info/WHEEL
keylimiter-0.1.5.dist-info/RECORD
