Metadata-Version: 2.1
Name: keylimiter
Version: 0.1.5
Summary: Thread-safe rate limiter algorithms
Author: Gabriel F Cipriano
Author-email: gabrielfcipriano@gmail.com.br
Requires-Python: >=3.8,<4.0
Classifier: Programming Language :: Python :: 3
Classifier: Programming Language :: Python :: 3.8
Classifier: Programming Language :: Python :: 3.9
Classifier: Programming Language :: Python :: 3.10
Classifier: Programming Language :: Python :: 3.11
Classifier: Programming Language :: Python :: 3.12
